fireant/__init__.py
fireant/exceptions.py
fireant/formats.py
fireant/reference_helpers.py
fireant/utils.py
fireant/database/__init__.py
fireant/database/base.py
fireant/database/column.py
fireant/database/mssql.py
fireant/database/mysql.py
fireant/database/postgresql.py
fireant/database/redshift.py
fireant/database/snowflake.py
fireant/database/sql_types.py
fireant/database/type_engine.py
fireant/database/vertica.py
fireant/dataset/__init__.py
fireant/dataset/annotations.py
fireant/dataset/data_blending.py
fireant/dataset/fields.py
fireant/dataset/filters.py
fireant/dataset/intervals.py
fireant/dataset/joins.py
fireant/dataset/klass.py
fireant/dataset/modifiers.py
fireant/dataset/operations.py
fireant/dataset/references.py
fireant/dataset/totals.py
fireant/middleware/__init__.py
fireant/middleware/concurrency.py
fireant/middleware/decorators.py
fireant/middleware/slow_query_logger.py
fireant/queries/__init__.py
fireant/queries/execution.py
fireant/queries/finders.py
fireant/queries/pagination.py
fireant/queries/pandas_workaround.py
fireant/queries/references.py
fireant/queries/sets.py
fireant/queries/special_cases.py
fireant/queries/totals_helper.py
fireant/queries/builder/__init__.py
fireant/queries/builder/dataset_blender_query_builder.py
fireant/queries/builder/dataset_query_builder.py
fireant/queries/builder/dimension_choices_query_builder.py
fireant/queries/builder/dimension_latest_query_builder.py
fireant/queries/builder/query_builder.py
fireant/tests/__init__.py
fireant/tests/test_fireant.py
fireant/tests/test_formats.py
fireant/tests/test_middleware.py
fireant/tests/test_reference_helpers.py
fireant/tests/test_utils.py
fireant/tests/database/__init__.py
fireant/tests/database/mock_database.py
fireant/tests/database/test_base_database.py
fireant/tests/database/test_columns.py
fireant/tests/database/test_fetch.py
fireant/tests/database/test_mssql.py
fireant/tests/database/test_mysql.py
fireant/tests/database/test_pickle.py
fireant-8.1.0.dist-info/METADATA
fireant-8.1.0.dist-info/WHEEL
fireant-8.1.0.dist-info/licenses/LICENSE.txt
fireant-8.1.0.dist-info/RECORD
