Metadata-Version: 2.4
Name: fireant
Version: 8.1.0
Summary: Data analysis tool for quickly building charts, tables, reports, and dashboards
Project-URL: Homepage, https://github.com/kayak/fireant
Project-URL: Documentation, https://fireant.readthedocs.io
Project-URL: Repository, https://github.com/kayak/fireant
Author-email: "KAYAK, GmbH" <bandit@kayak.com>
Maintainer-email: Ąžuolas Krušna <akrusna@kayak.com>
License-Expression: Apache-2.0
License-File: LICENSE.txt
Keywords: analytics,bi,builder,data,fireant,mssql,mysql,pandas,postgres,python,query,querybuilder,science,sql,vertica
Requires-Python: >=3.9
Requires-Dist: pandas>=2.0.0
Requires-Dist: pypika<1.0.0,>=0.50.0
Requires-Dist: toposort<2,>=1.6
Provides-Extra: ipython
Requires-Dist: ipython<9,>=7.11; extra == 'ipython'
Requires-Dist: matplotlib<4,>=3.1.0; extra == 'ipython'
Provides-Extra: mssql
Requires-Dist: cython<4,>=3.0.0; extra == 'mssql'
Requires-Dist: pymssql<3,>=2.2.0; extra == 'mssql'
Provides-Extra: mysql
Requires-Dist: pymysql<2,>=1.0.0; extra == 'mysql'
Provides-Extra: postgresql
Requires-Dist: psycopg2-binary<3,>=2.9.11; extra == 'postgresql'
Provides-Extra: redshift
Requires-Dist: psycopg2-binary<3,>=2.9.11; extra == 'redshift'
Provides-Extra: snowflake
Requires-Dist: snowflake-connector-python<4,>=3.0.0; extra == 'snowflake'
Provides-Extra: vertica
Requires-Dist: vertica-python<2,>=1.0.0; extra == 'vertica'
